weao_api/__init__.py
weao_api/client.py
weao_api/exceptions.py
weao_api-0.1.0.dist-info/METADATA
weao_api-0.1.0.dist-info/WHEEL
weao_api-0.1.0.dist-info/top_level.txt
weao_api-0.1.0.dist-info/RECORD
